{
  "frame": 66689,
  "step": 420,
  "ego": {
    "location": {
      "x": -46.862,
      "y": -57.507,
      "z": 0.002
    },
    "rotation": {
      "pitch": 0.045,
      "yaw": -107.808,
      "roll": 0.028
    },
    "velocity": {
      "x": -1.773,
      "y": -4.728
    },
    "speed_kmh": 18.18
  },
  "risk": {
    "score": 0.5,
    "level": "high",
    "ttc_min_s": 1.22,
    "min_dist_m": 4.14,
    "top_threats": [
      {
        "actor_id": "p10",
        "actor_type": "pedestrian",
        "dist_m": 4.14,
        "fwd_m": 2.63,
        "lat_m": 3.19,
        "ttc_s": 1.22,
        "closing_ms": 3.39,
        "speed_ms": 0.0,
        "risk": 0.5
      },
      {
        "actor_id": "v150",
        "actor_type": "vehicle",
        "dist_m": 11.58,
        "fwd_m": 9.25,
        "lat_m": 6.95,
        "ttc_s": 2.24,
        "closing_ms": 5.17,
        "speed_ms": 4.03,
        "risk": 0.4
      },
      {
        "actor_id": "v132",
        "actor_type": "vehicle",
        "dist_m": 10.98,
        "fwd_m": 10.42,
        "lat_m": 3.45,
        "ttc_s": 2.33,
        "closing_ms": 4.7,
        "speed_ms": 6.22,
        "risk": 0.4
      },
      {
        "actor_id": "v144",
        "actor_type": "vehicle",
        "dist_m": 7.54,
        "fwd_m": 6.79,
        "lat_m": 3.27,
        "ttc_s": 1.54,
        "closing_ms": 4.88,
        "speed_ms": 3.46,
        "risk": 0.4
      }
    ]
  },
  "scenario": "normal",
  "vehicles": [
    {
      "id": "v19",
      "type": "vehicle",
      "blueprint": "vehicle.nissan.patrol",
      "loc": {
        "x": -52.126,
        "y": -45.645,
        "z": 0.3
      },
      "yaw": 90.43,
      "velocity": {
        "x": 0.0,
        "y": 0.0
      },
      "speed_ms": 0.0
    },
    {
      "id": "v5",
      "type": "vehicle",
      "blueprint": "vehicle.nissan.patrol",
      "loc": {
        "x": -45.212,
        "y": -34.163,
        "z": 0.3
      },
      "yaw": -89.57,
      "velocity": {
        "x": 0.0,
        "y": 0.0
      },
      "speed_ms": 0.0
    },
    {
      "id": "v38",
      "type": "vehicle",
      "blueprint": "vehicle.mercedes.coupe",
      "loc": {
        "x": -57.165,
        "y": -68.59,
        "z": 0.3
      },
      "yaw": -179.4,
      "velocity": {
        "x": 0.0,
        "y": 0.0
      },
      "speed_ms": 0.0
    },
    {
      "id": "v100",
      "type": "vehicle",
      "blueprint": "vehicle.volkswagen.t2_2021",
      "loc": {
        "x": -59.213,
        "y": -68.612,
        "z": 0.3
      },
      "yaw": -179.4,
      "velocity": {
        "x": 0.0,
        "y": 0.0
      },
      "speed_ms": 0.0
    },
    {
      "id": "v102",
      "type": "vehicle",
      "blueprint": "vehicle.dodge.charger_police",
      "loc": {
        "x": -55.522,
        "y": -68.573,
        "z": 0.3
      },
      "yaw": -179.4,
      "velocity": {
        "x": 0.0,
        "y": 0.0
      },
      "speed_ms": 0.0
    },
    {
      "id": "v103",
      "type": "vehicle",
      "blueprint": "vehicle.mercedes.coupe_2020",
      "loc": {
        "x": -41.761,
        "y": -27.585,
        "z": 0.3
      },
      "yaw": -89.57,
      "velocity": {
        "x": 0.0,
        "y": 0.0
      },
      "speed_ms": 0.0
    },
    {
      "id": "v105",
      "type": "vehicle",
      "blueprint": "vehicle.ford.mustang",
      "loc": {
        "x": -54.345,
        "y": -68.561,
        "z": 0.3
      },
      "yaw": -179.4,
      "velocity": {
        "x": 0.0,
        "y": 0.0
      },
      "speed_ms": 0.0
    },
    {
      "id": "v123",
      "type": "vehicle",
      "blueprint": "vehicle.nissan.patrol",
      "loc": {
        "x": -52.552,
        "y": -68.542,
        "z": 0.3
      },
      "yaw": -179.4,
      "velocity": {
        "x": 0.0,
        "y": 0.0
      },
      "speed_ms": 0.0
    },
    {
      "id": "v112",
      "type": "vehicle",
      "blueprint": "vehicle.volkswagen.t2",
      "loc": {
        "x": -41.271,
        "y": -50.632,
        "z": 0.3
      },
      "yaw": -77.56,
      "velocity": {
        "x": 0.0,
        "y": 0.0
      },
      "speed_ms": 0.0
    },
    {
      "id": "v116",
      "type": "vehicle",
      "blueprint": "vehicle.toyota.prius",
      "loc": {
        "x": -39.451,
        "y": -51.216,
        "z": 0.3
      },
      "yaw": -59.11,
      "velocity": {
        "x": 0.0,
        "y": 0.0
      },
      "speed_ms": 0.0
    },
    {
      "id": "v150",
      "type": "vehicle",
      "blueprint": "vehicle.volkswagen.t2",
      "loc": {
        "x": -43.072,
        "y": -68.443,
        "z": 0.3
      },
      "yaw": -179.4,
      "velocity": {
        "x": 0.0,
        "y": 0.0
      },
      "speed_ms": 0.0
    },
    {
      "id": "v135",
      "type": "vehicle",
      "blueprint": "vehicle.audi.etron",
      "loc": {
        "x": -56.429,
        "y": -65.082,
        "z": 0.3
      },
      "yaw": -179.4,
      "velocity": {
        "x": 0.0,
        "y": 0.0
      },
      "speed_ms": 0.0
    },
    {
      "id": "v199",
      "type": "vehicle",
      "blueprint": "vehicle.micro.microlino",
      "loc": {
        "x": -64.08,
        "y": -68.662,
        "z": 0.3
      },
      "yaw": -179.4,
      "velocity": {
        "x": 0.0,
        "y": 0.0
      },
      "speed_ms": 0.0
    },
    {
      "id": "v113",
      "type": "vehicle",
      "blueprint": "vehicle.lincoln.mkz_2020",
      "loc": {
        "x": -41.745,
        "y": -29.718,
        "z": 0.3
      },
      "yaw": -89.57,
      "velocity": {
        "x": 0.0,
        "y": 0.0
      },
      "speed_ms": 0.0
    },
    {
      "id": "v134",
      "type": "vehicle",
      "blueprint": "vehicle.dodge.charger_police_2020",
      "loc": {
        "x": -60.083,
        "y": -68.621,
        "z": 0.3
      },
      "yaw": -179.4,
      "velocity": {
        "x": 0.0,
        "y": 0.0
      },
      "speed_ms": 0.0
    },
    {
      "id": "v128",
      "type": "vehicle",
      "blueprint": "vehicle.volkswagen.t2_2021",
      "loc": {
        "x": -48.567,
        "y": -48.585,
        "z": 0.3
      },
      "yaw": 93.82,
      "velocity": {
        "x": 0.0,
        "y": 0.0
      },
      "speed_ms": 0.0
    },
    {
      "id": "v170",
      "type": "vehicle",
      "blueprint": "vehicle.micro.microlino",
      "loc": {
        "x": -41.659,
        "y": -41.147,
        "z": 0.3
      },
      "yaw": -89.57,
      "velocity": {
        "x": 0.0,
        "y": 0.0
      },
      "speed_ms": 0.0
    },
    {
      "id": "v132",
      "type": "vehicle",
      "blueprint": "vehicle.mercedes.coupe",
      "loc": {
        "x": -46.762,
        "y": -68.482,
        "z": 0.3
      },
      "yaw": -179.4,
      "velocity": {
        "x": 0.0,
        "y": 0.0
      },
      "speed_ms": 0.0
    },
    {
      "id": "v136",
      "type": "vehicle",
      "blueprint": "vehicle.bmw.grandtourer",
      "loc": {
        "x": -45.175,
        "y": -39.04,
        "z": 0.3
      },
      "yaw": -89.57,
      "velocity": {
        "x": 0.0,
        "y": 0.0
      },
      "speed_ms": 0.0
    },
    {
      "id": "v137",
      "type": "vehicle",
      "blueprint": "vehicle.dodge.charger_2020",
      "loc": {
        "x": -41.646,
        "y": -42.937,
        "z": 0.3
      },
      "yaw": -89.57,
      "velocity": {
        "x": 0.0,
        "y": 0.0
      },
      "speed_ms": 0.0
    },
    {
      "id": "v139",
      "type": "vehicle",
      "blueprint": "vehicle.mini.cooper_s",
      "loc": {
        "x": -45.095,
        "y": -49.633,
        "z": 0.3
      },
      "yaw": -89.7,
      "velocity": {
        "x": 0.0,
        "y": 0.0
      },
      "speed_ms": 0.0
    },
    {
      "id": "v138",
      "type": "vehicle",
      "blueprint": "vehicle.dodge.charger_police_2020",
      "loc": {
        "x": -41.825,
        "y": -19.127,
        "z": 0.3
      },
      "yaw": -89.57,
      "velocity": {
        "x": 0.0,
        "y": 0.0
      },
      "speed_ms": 0.0
    },
    {
      "id": "v140",
      "type": "vehicle",
      "blueprint": "vehicle.ford.mustang",
      "loc": {
        "x": -41.718,
        "y": -33.413,
        "z": 0.3
      },
      "yaw": -89.57,
      "velocity": {
        "x": 0.0,
        "y": 0.0
      },
      "speed_ms": 0.0
    },
    {
      "id": "v251",
      "type": "vehicle",
      "blueprint": "vehicle.micro.microlino",
      "loc": {
        "x": -52.484,
        "y": -65.041,
        "z": 0.3
      },
      "yaw": -179.4,
      "velocity": {
        "x": 0.0,
        "y": 0.0
      },
      "speed_ms": 0.0
    },
    {
      "id": "v154",
      "type": "vehicle",
      "blueprint": "vehicle.volkswagen.t2_2021",
      "loc": {
        "x": -41.68,
        "y": -38.404,
        "z": 0.3
      },
      "yaw": -89.57,
      "velocity": {
        "x": 0.0,
        "y": 0.0
      },
      "speed_ms": 0.0
    },
    {
      "id": "v144",
      "type": "vehicle",
      "blueprint": "vehicle.bmw.grandtourer",
      "loc": {
        "x": -45.823,
        "y": -64.972,
        "z": 0.3
      },
      "yaw": -179.4,
      "velocity": {
        "x": 0.0,
        "y": 0.0
      },
      "speed_ms": 0.0
    }
  ],
  "pedestrians": [
    {
      "id": "p0",
      "type": "pedestrian",
      "blueprint": "walker.pedestrian.0051",
      "loc": {
        "x": -30.451,
        "y": 2.081,
        "z": 1.089
      },
      "yaw": 7.38,
      "velocity": {
        "x": 0.0,
        "y": 0.0
      },
      "speed_ms": 0.0
    },
    {
      "id": "p1",
      "type": "pedestrian",
      "blueprint": "walker.pedestrian.0003",
      "loc": {
        "x": -60.816,
        "y": -25.876,
        "z": 1.089
      },
      "yaw": 84.84,
      "velocity": {
        "x": 0.0,
        "y": 0.0
      },
      "speed_ms": 0.0
    },
    {
      "id": "p10",
      "type": "pedestrian",
      "blueprint": "walker.pedestrian.0004",
      "loc": {
        "x": -50.706,
        "y": -59.033,
        "z": 0.302
      },
      "yaw": -19.22,
      "velocity": {
        "x": 0.0,
        "y": 0.0
      },
      "speed_ms": 0.0
    },
    {
      "id": "p11",
      "type": "pedestrian",
      "blueprint": "walker.pedestrian.0051",
      "loc": {
        "x": -34.088,
        "y": -1.209,
        "z": 1.089
      },
      "yaw": 80.71,
      "velocity": {
        "x": 0.0,
        "y": 0.0
      },
      "speed_ms": 0.0
    },
    {
      "id": "p12",
      "type": "pedestrian",
      "blueprint": "walker.pedestrian.0022",
      "loc": {
        "x": -34.533,
        "y": -33.104,
        "z": 1.089
      },
      "yaw": -108.19,
      "velocity": {
        "x": 0.0,
        "y": 0.0
      },
      "speed_ms": 0.0
    },
    {
      "id": "p13",
      "type": "pedestrian",
      "blueprint": "walker.pedestrian.0018",
      "loc": {
        "x": -33.698,
        "y": -46.231,
        "z": 1.089
      },
      "yaw": -66.69,
      "velocity": {
        "x": 0.0,
        "y": 0.0
      },
      "speed_ms": 0.0
    },
    {
      "id": "p14",
      "type": "pedestrian",
      "blueprint": "walker.pedestrian.0017",
      "loc": {
        "x": -67.657,
        "y": 4.238,
        "z": 1.089
      },
      "yaw": -7.1,
      "velocity": {
        "x": 0.0,
        "y": 0.0
      },
      "speed_ms": 0.0
    },
    {
      "id": "p15",
      "type": "pedestrian",
      "blueprint": "walker.pedestrian.0008",
      "loc": {
        "x": -60.622,
        "y": -8.309,
        "z": 1.089
      },
      "yaw": 91.98,
      "velocity": {
        "x": 0.0,
        "y": 0.0
      },
      "speed_ms": 0.0
    },
    {
      "id": "p16",
      "type": "pedestrian",
      "blueprint": "walker.pedestrian.0051",
      "loc": {
        "x": -33.304,
        "y": -41.637,
        "z": 1.089
      },
      "yaw": -97.37,
      "velocity": {
        "x": 0.0,
        "y": 0.0
      },
      "speed_ms": 0.0
    },
    {
      "id": "p17",
      "type": "pedestrian",
      "blueprint": "walker.pedestrian.0029",
      "loc": {
        "x": -35.341,
        "y": -42.04,
        "z": 1.089
      },
      "yaw": 83.55,
      "velocity": {
        "x": 0.0,
        "y": 0.0
      },
      "speed_ms": 0.0
    },
    {
      "id": "p18",
      "type": "pedestrian",
      "blueprint": "walker.pedestrian.0009",
      "loc": {
        "x": -61.211,
        "y": -11.437,
        "z": 0.709
      },
      "yaw": 96.29,
      "velocity": {
        "x": 0.0,
        "y": 0.0
      },
      "speed_ms": 0.0
    },
    {
      "id": "p19",
      "type": "pedestrian",
      "blueprint": "walker.pedestrian.0025",
      "loc": {
        "x": -58.483,
        "y": -45.602,
        "z": 1.089
      },
      "yaw": -173.4,
      "velocity": {
        "x": 0.0,
        "y": 0.0
      },
      "speed_ms": 0.0
    },
    {
      "id": "p2",
      "type": "pedestrian",
      "blueprint": "walker.pedestrian.0038",
      "loc": {
        "x": -57.95,
        "y": -44.734,
        "z": 1.089
      },
      "yaw": -73.46,
      "velocity": {
        "x": 0.0,
        "y": 0.0
      },
      "speed_ms": 0.0
    },
    {
      "id": "p20",
      "type": "pedestrian",
      "blueprint": "walker.pedestrian.0036",
      "loc": {
        "x": -51.739,
        "y": -48.3,
        "z": 0.987
      },
      "yaw": -55.83,
      "velocity": {
        "x": 0.0,
        "y": 0.0
      },
      "speed_ms": 0.0
    },
    {
      "id": "p21",
      "type": "pedestrian",
      "blueprint": "walker.pedestrian.0015",
      "loc": {
        "x": -30.92,
        "y": -64.03,
        "z": 0.939
      },
      "yaw": -95.36,
      "velocity": {
        "x": 0.0,
        "y": 0.0
      },
      "speed_ms": 0.0
    },
    {
      "id": "p22",
      "type": "pedestrian",
      "blueprint": "walker.pedestrian.0016",
      "loc": {
        "x": -50.91,
        "y": -48.578,
        "z": 0.953
      },
      "yaw": -107.02,
      "velocity": {
        "x": 0.0,
        "y": 0.0
      },
      "speed_ms": 0.0
    },
    {
      "id": "p24",
      "type": "pedestrian",
      "blueprint": "walker.pedestrian.0038",
      "loc": {
        "x": -34.864,
        "y": -31.788,
        "z": 1.089
      },
      "yaw": 83.24,
      "velocity": {
        "x": 0.0,
        "y": 0.0
      },
      "speed_ms": 0.0
    }
  ],
  "total_actors": 43,
  "sensors": {
    "rgb": {
      "file": "rgb/066689.png",
      "width": 800,
      "height": 600,
      "fov": 90
    },
    "depth": {
      "file": "depth/066689.png",
      "unit": "mm_uint16",
      "fx": 400.0,
      "fy": 300.0,
      "cx": 400,
      "cy": 300
    },
    "lidar": {
      "file": "lidar/066689.npy",
      "columns": [
        "x",
        "y",
        "z",
        "intensity"
      ],
      "num_points": 29511
    }
  },
  "yolo_detections": []
}