{
  "frame": 66673,
  "step": 404,
  "ego": {
    "location": {
      "x": -45.944,
      "y": -54.527,
      "z": 0.002
    },
    "rotation": {
      "pitch": -0.0,
      "yaw": -100.249,
      "roll": 0.031
    },
    "velocity": {
      "x": -0.845,
      "y": -3.178
    },
    "speed_kmh": 11.84
  },
  "risk": {
    "score": 0.5,
    "level": "high",
    "ttc_min_s": 2.1,
    "min_dist_m": 6.56,
    "top_threats": [
      {
        "actor_id": "p10",
        "actor_type": "pedestrian",
        "dist_m": 6.56,
        "fwd_m": 5.28,
        "lat_m": 3.88,
        "ttc_s": 2.34,
        "closing_ms": 2.8,
        "speed_ms": 0.0,
        "risk": 0.5
      },
      {
        "actor_id": "v144",
        "actor_type": "vehicle",
        "dist_m": 7.24,
        "fwd_m": 6.44,
        "lat_m": 3.32,
        "ttc_s": 2.1,
        "closing_ms": 3.44,
        "speed_ms": 2.3,
        "risk": 0.4
      },
      {
        "actor_id": "v123",
        "actor_type": "vehicle",
        "dist_m": 14.08,
        "fwd_m": 14.06,
        "lat_m": 0.75,
        "ttc_s": 5.81,
        "closing_ms": 2.42,
        "speed_ms": 6.16,
        "risk": 0.3721
      },
      {
        "actor_id": "v131",
        "actor_type": "vehicle",
        "dist_m": 14.2,
        "fwd_m": 14.2,
        "lat_m": 0.01,
        "ttc_s": 5.38,
        "closing_ms": 2.64,
        "speed_ms": 3.42,
        "risk": 0.3673
      },
      {
        "actor_id": "v105",
        "actor_type": "vehicle",
        "dist_m": 14.64,
        "fwd_m": 14.53,
        "lat_m": 1.75,
        "ttc_s": 8.56,
        "closing_ms": 1.71,
        "speed_ms": 5.17,
        "risk": 0.3558
      },
      {
        "actor_id": "v150",
        "actor_type": "vehicle",
        "dist_m": 11.64,
        "fwd_m": 9.29,
        "lat_m": 7.0,
        "ttc_s": 3.17,
        "closing_ms": 3.68,
        "speed_ms": 2.76,
        "risk": 0.3001
      },
      {
        "actor_id": "v132",
        "actor_type": "vehicle",
        "dist_m": 14.26,
        "fwd_m": 13.14,
        "lat_m": 5.54,
        "ttc_s": 3.63,
        "closing_ms": 3.93,
        "speed_ms": 4.87,
        "risk": 0.2301
      }
    ]
  },
  "scenario": "normal",
  "vehicles": [
    {
      "id": "v19",
      "type": "vehicle",
      "blueprint": "vehicle.nissan.patrol",
      "loc": {
        "x": -52.143,
        "y": -43.333,
        "z": 0.3
      },
      "yaw": 90.43,
      "velocity": {
        "x": 0.0,
        "y": 0.0
      },
      "speed_ms": 0.0
    },
    {
      "id": "v5",
      "type": "vehicle",
      "blueprint": "vehicle.nissan.patrol",
      "loc": {
        "x": -48.732,
        "y": -31.497,
        "z": 0.3
      },
      "yaw": 90.43,
      "velocity": {
        "x": 0.0,
        "y": 0.0
      },
      "speed_ms": 0.0
    },
    {
      "id": "v38",
      "type": "vehicle",
      "blueprint": "vehicle.mercedes.coupe",
      "loc": {
        "x": -50.408,
        "y": -68.52,
        "z": 0.3
      },
      "yaw": -179.4,
      "velocity": {
        "x": 0.0,
        "y": 0.0
      },
      "speed_ms": 0.0
    },
    {
      "id": "v100",
      "type": "vehicle",
      "blueprint": "vehicle.volkswagen.t2_2021",
      "loc": {
        "x": -54.596,
        "y": -68.564,
        "z": 0.3
      },
      "yaw": -179.4,
      "velocity": {
        "x": 0.0,
        "y": 0.0
      },
      "speed_ms": 0.0
    },
    {
      "id": "v102",
      "type": "vehicle",
      "blueprint": "vehicle.dodge.charger_police",
      "loc": {
        "x": -52.438,
        "y": -68.541,
        "z": 0.3
      },
      "yaw": -179.4,
      "velocity": {
        "x": 0.0,
        "y": 0.0
      },
      "speed_ms": 0.0
    },
    {
      "id": "v103",
      "type": "vehicle",
      "blueprint": "vehicle.mercedes.coupe_2020",
      "loc": {
        "x": -45.287,
        "y": -24.216,
        "z": 0.3
      },
      "yaw": -89.57,
      "velocity": {
        "x": 0.0,
        "y": 0.0
      },
      "speed_ms": 0.0
    },
    {
      "id": "v105",
      "type": "vehicle",
      "blueprint": "vehicle.ford.mustang",
      "loc": {
        "x": -50.254,
        "y": -68.518,
        "z": 0.3
      },
      "yaw": -179.4,
      "velocity": {
        "x": 0.0,
        "y": 0.0
      },
      "speed_ms": 0.0
    },
    {
      "id": "v127",
      "type": "vehicle",
      "blueprint": "vehicle.mini.cooper_s",
      "loc": {
        "x": -45.552,
        "y": -68.469,
        "z": 0.3
      },
      "yaw": -179.4,
      "velocity": {
        "x": 0.0,
        "y": 0.0
      },
      "speed_ms": 0.0
    },
    {
      "id": "v123",
      "type": "vehicle",
      "blueprint": "vehicle.nissan.patrol",
      "loc": {
        "x": -47.711,
        "y": -68.492,
        "z": 0.3
      },
      "yaw": -179.4,
      "velocity": {
        "x": 0.0,
        "y": 0.0
      },
      "speed_ms": 0.0
    },
    {
      "id": "v112",
      "type": "vehicle",
      "blueprint": "vehicle.volkswagen.t2",
      "loc": {
        "x": -41.171,
        "y": -47.072,
        "z": 0.3
      },
      "yaw": -75.81,
      "velocity": {
        "x": 0.0,
        "y": 0.0
      },
      "speed_ms": 0.0
    },
    {
      "id": "v131",
      "type": "vehicle",
      "blueprint": "vehicle.audi.a2",
      "loc": {
        "x": -48.456,
        "y": -68.5,
        "z": 0.3
      },
      "yaw": -179.4,
      "velocity": {
        "x": 0.0,
        "y": 0.0
      },
      "speed_ms": 0.0
    },
    {
      "id": "v116",
      "type": "vehicle",
      "blueprint": "vehicle.toyota.prius",
      "loc": {
        "x": -41.309,
        "y": -46.475,
        "z": 0.3
      },
      "yaw": -78.08,
      "velocity": {
        "x": 0.0,
        "y": 0.0
      },
      "speed_ms": 0.0
    },
    {
      "id": "v150",
      "type": "vehicle",
      "blueprint": "vehicle.volkswagen.t2",
      "loc": {
        "x": -40.707,
        "y": -64.919,
        "z": 0.3
      },
      "yaw": -179.4,
      "velocity": {
        "x": 0.0,
        "y": 0.0
      },
      "speed_ms": 0.0
    },
    {
      "id": "v135",
      "type": "vehicle",
      "blueprint": "vehicle.audi.etron",
      "loc": {
        "x": -54.38,
        "y": -63.466,
        "z": 0.3
      },
      "yaw": -153.86,
      "velocity": {
        "x": 0.0,
        "y": 0.0
      },
      "speed_ms": 0.0
    },
    {
      "id": "v199",
      "type": "vehicle",
      "blueprint": "vehicle.micro.microlino",
      "loc": {
        "x": -58.938,
        "y": -68.609,
        "z": 0.3
      },
      "yaw": -179.4,
      "velocity": {
        "x": 0.0,
        "y": 0.0
      },
      "speed_ms": 0.0
    },
    {
      "id": "v113",
      "type": "vehicle",
      "blueprint": "vehicle.lincoln.mkz_2020",
      "loc": {
        "x": -41.778,
        "y": -25.429,
        "z": 0.3
      },
      "yaw": -89.57,
      "velocity": {
        "x": 0.0,
        "y": 0.0
      },
      "speed_ms": 0.0
    },
    {
      "id": "v134",
      "type": "vehicle",
      "blueprint": "vehicle.dodge.charger_police_2020",
      "loc": {
        "x": -56.6,
        "y": -68.584,
        "z": 0.3
      },
      "yaw": -179.4,
      "velocity": {
        "x": 0.0,
        "y": 0.0
      },
      "speed_ms": 0.0
    },
    {
      "id": "v128",
      "type": "vehicle",
      "blueprint": "vehicle.volkswagen.t2_2021",
      "loc": {
        "x": -48.624,
        "y": -45.895,
        "z": 0.3
      },
      "yaw": 90.43,
      "velocity": {
        "x": 0.0,
        "y": 0.0
      },
      "speed_ms": 0.0
    },
    {
      "id": "v170",
      "type": "vehicle",
      "blueprint": "vehicle.micro.microlino",
      "loc": {
        "x": -41.689,
        "y": -37.239,
        "z": 0.3
      },
      "yaw": -89.57,
      "velocity": {
        "x": 0.0,
        "y": 0.0
      },
      "speed_ms": 0.0
    },
    {
      "id": "v132",
      "type": "vehicle",
      "blueprint": "vehicle.mercedes.coupe",
      "loc": {
        "x": -42.829,
        "y": -68.441,
        "z": 0.3
      },
      "yaw": -179.4,
      "velocity": {
        "x": 0.0,
        "y": 0.0
      },
      "speed_ms": 0.0
    },
    {
      "id": "v136",
      "type": "vehicle",
      "blueprint": "vehicle.bmw.grandtourer",
      "loc": {
        "x": -45.198,
        "y": -36.026,
        "z": 0.3
      },
      "yaw": -89.57,
      "velocity": {
        "x": 0.0,
        "y": 0.0
      },
      "speed_ms": 0.0
    },
    {
      "id": "v137",
      "type": "vehicle",
      "blueprint": "vehicle.dodge.charger_2020",
      "loc": {
        "x": -41.671,
        "y": -39.572,
        "z": 0.3
      },
      "yaw": -89.57,
      "velocity": {
        "x": 0.0,
        "y": 0.0
      },
      "speed_ms": 0.0
    },
    {
      "id": "v139",
      "type": "vehicle",
      "blueprint": "vehicle.mini.cooper_s",
      "loc": {
        "x": -45.119,
        "y": -46.487,
        "z": 0.3
      },
      "yaw": -89.57,
      "velocity": {
        "x": 0.0,
        "y": 0.0
      },
      "speed_ms": 0.0
    },
    {
      "id": "v138",
      "type": "vehicle",
      "blueprint": "vehicle.dodge.charger_police_2020",
      "loc": {
        "x": -41.852,
        "y": -14.913,
        "z": 0.3
      },
      "yaw": -89.84,
      "velocity": {
        "x": 0.0,
        "y": 0.0
      },
      "speed_ms": 0.0
    },
    {
      "id": "v140",
      "type": "vehicle",
      "blueprint": "vehicle.ford.mustang",
      "loc": {
        "x": -41.745,
        "y": -29.73,
        "z": 0.3
      },
      "yaw": -89.57,
      "velocity": {
        "x": 0.0,
        "y": 0.0
      },
      "speed_ms": 0.0
    },
    {
      "id": "v251",
      "type": "vehicle",
      "blueprint": "vehicle.micro.microlino",
      "loc": {
        "x": -50.712,
        "y": -61.523,
        "z": 0.3
      },
      "yaw": 0.6,
      "velocity": {
        "x": 0.0,
        "y": 0.0
      },
      "speed_ms": 0.0
    },
    {
      "id": "v154",
      "type": "vehicle",
      "blueprint": "vehicle.volkswagen.t2_2021",
      "loc": {
        "x": -41.714,
        "y": -33.922,
        "z": 0.3
      },
      "yaw": -89.57,
      "velocity": {
        "x": 0.0,
        "y": 0.0
      },
      "speed_ms": 0.0
    },
    {
      "id": "v144",
      "type": "vehicle",
      "blueprint": "vehicle.bmw.grandtourer",
      "loc": {
        "x": -43.827,
        "y": -61.451,
        "z": 0.3
      },
      "yaw": 0.6,
      "velocity": {
        "x": 0.0,
        "y": 0.0
      },
      "speed_ms": 0.0
    }
  ],
  "pedestrians": [
    {
      "id": "p0",
      "type": "pedestrian",
      "blueprint": "walker.pedestrian.0051",
      "loc": {
        "x": -31.642,
        "y": 1.76,
        "z": 1.089
      },
      "yaw": 25.7,
      "velocity": {
        "x": 0.0,
        "y": 0.0
      },
      "speed_ms": 0.0
    },
    {
      "id": "p1",
      "type": "pedestrian",
      "blueprint": "walker.pedestrian.0003",
      "loc": {
        "x": -60.945,
        "y": -27.31,
        "z": 1.089
      },
      "yaw": 84.94,
      "velocity": {
        "x": 0.0,
        "y": 0.0
      },
      "speed_ms": 0.0
    },
    {
      "id": "p10",
      "type": "pedestrian",
      "blueprint": "walker.pedestrian.0004",
      "loc": {
        "x": -50.706,
        "y": -59.033,
        "z": 0.302
      },
      "yaw": -19.22,
      "velocity": {
        "x": 0.0,
        "y": 0.0
      },
      "speed_ms": 0.0
    },
    {
      "id": "p11",
      "type": "pedestrian",
      "blueprint": "walker.pedestrian.0051",
      "loc": {
        "x": -34.264,
        "y": -2.38,
        "z": 1.089
      },
      "yaw": 81.99,
      "velocity": {
        "x": 0.0,
        "y": 0.0
      },
      "speed_ms": 0.0
    },
    {
      "id": "p12",
      "type": "pedestrian",
      "blueprint": "walker.pedestrian.0022",
      "loc": {
        "x": -34.276,
        "y": -31.802,
        "z": 1.089
      },
      "yaw": -93.45,
      "velocity": {
        "x": 0.0,
        "y": 0.0
      },
      "speed_ms": 0.0
    },
    {
      "id": "p13",
      "type": "pedestrian",
      "blueprint": "walker.pedestrian.0018",
      "loc": {
        "x": -34.223,
        "y": -45.053,
        "z": 1.089
      },
      "yaw": -64.58,
      "velocity": {
        "x": 0.0,
        "y": 0.0
      },
      "speed_ms": 0.0
    },
    {
      "id": "p14",
      "type": "pedestrian",
      "blueprint": "walker.pedestrian.0017",
      "loc": {
        "x": -69.086,
        "y": 4.413,
        "z": 1.089
      },
      "yaw": -50.17,
      "velocity": {
        "x": 0.0,
        "y": 0.0
      },
      "speed_ms": 0.0
    },
    {
      "id": "p15",
      "type": "pedestrian",
      "blueprint": "walker.pedestrian.0008",
      "loc": {
        "x": -60.557,
        "y": -9.463,
        "z": 1.089
      },
      "yaw": 93.9,
      "velocity": {
        "x": 0.0,
        "y": 0.0
      },
      "speed_ms": 0.0
    },
    {
      "id": "p16",
      "type": "pedestrian",
      "blueprint": "walker.pedestrian.0051",
      "loc": {
        "x": -33.177,
        "y": -40.241,
        "z": 1.089
      },
      "yaw": -94.73,
      "velocity": {
        "x": 0.0,
        "y": 0.0
      },
      "speed_ms": 0.0
    },
    {
      "id": "p17",
      "type": "pedestrian",
      "blueprint": "walker.pedestrian.0029",
      "loc": {
        "x": -35.53,
        "y": -43.447,
        "z": 1.089
      },
      "yaw": 82.97,
      "velocity": {
        "x": 0.0,
        "y": 0.0
      },
      "speed_ms": 0.0
    },
    {
      "id": "p18",
      "type": "pedestrian",
      "blueprint": "walker.pedestrian.0009",
      "loc": {
        "x": -61.264,
        "y": -12.502,
        "z": 0.709
      },
      "yaw": 79.32,
      "velocity": {
        "x": 0.0,
        "y": 0.0
      },
      "speed_ms": 0.0
    },
    {
      "id": "p19",
      "type": "pedestrian",
      "blueprint": "walker.pedestrian.0025",
      "loc": {
        "x": -57.58,
        "y": -45.154,
        "z": 1.089
      },
      "yaw": -83.38,
      "velocity": {
        "x": 0.0,
        "y": 0.0
      },
      "speed_ms": 0.0
    },
    {
      "id": "p2",
      "type": "pedestrian",
      "blueprint": "walker.pedestrian.0038",
      "loc": {
        "x": -58.271,
        "y": -43.492,
        "z": 1.089
      },
      "yaw": -77.53,
      "velocity": {
        "x": 0.0,
        "y": 0.0
      },
      "speed_ms": 0.0
    },
    {
      "id": "p20",
      "type": "pedestrian",
      "blueprint": "walker.pedestrian.0036",
      "loc": {
        "x": -51.917,
        "y": -48.026,
        "z": 1.014
      },
      "yaw": -17.37,
      "velocity": {
        "x": 0.0,
        "y": 0.0
      },
      "speed_ms": 0.0
    },
    {
      "id": "p21",
      "type": "pedestrian",
      "blueprint": "walker.pedestrian.0015",
      "loc": {
        "x": -30.786,
        "y": -62.596,
        "z": 0.939
      },
      "yaw": -91.59,
      "velocity": {
        "x": 0.0,
        "y": 0.0
      },
      "speed_ms": 0.0
    },
    {
      "id": "p22",
      "type": "pedestrian",
      "blueprint": "walker.pedestrian.0016",
      "loc": {
        "x": -50.89,
        "y": -48.359,
        "z": 0.974
      },
      "yaw": -22.87,
      "velocity": {
        "x": 0.0,
        "y": 0.0
      },
      "speed_ms": 0.0
    },
    {
      "id": "p24",
      "type": "pedestrian",
      "blueprint": "walker.pedestrian.0038",
      "loc": {
        "x": -35.008,
        "y": -33.199,
        "z": 1.089
      },
      "yaw": 85.31,
      "velocity": {
        "x": 0.0,
        "y": 0.0
      },
      "speed_ms": 0.0
    }
  ],
  "total_actors": 45,
  "sensors": {
    "rgb": {
      "file": "rgb/066673.png",
      "width": 800,
      "height": 600,
      "fov": 90
    },
    "depth": {
      "file": "depth/066673.png",
      "unit": "mm_uint16",
      "fx": 400.0,
      "fy": 300.0,
      "cx": 400,
      "cy": 300
    },
    "lidar": {
      "file": "lidar/066673.npy",
      "columns": [
        "x",
        "y",
        "z",
        "intensity"
      ],
      "num_points": 29671
    }
  },
  "yolo_detections": []
}