{
  "frame": 66729,
  "step": 460,
  "ego": {
    "location": {
      "x": -49.955,
      "y": -62.757,
      "z": 0.002
    },
    "rotation": {
      "pitch": -0.001,
      "yaw": -126.18,
      "roll": 0.015
    },
    "velocity": {
      "x": -2.117,
      "y": -2.483
    },
    "speed_kmh": 11.75
  },
  "risk": {
    "score": 0.4173,
    "level": "high",
    "ttc_min_s": 2.35,
    "min_dist_m": 5.15,
    "top_threats": [
      {
        "actor_id": "v150",
        "actor_type": "vehicle",
        "dist_m": 5.76,
        "fwd_m": 4.6,
        "lat_m": 3.46,
        "ttc_s": 2.35,
        "closing_ms": 2.45,
        "speed_ms": 0.0,
        "risk": 0.4173
      },
      {
        "actor_id": "v251",
        "actor_type": "vehicle",
        "dist_m": 8.75,
        "fwd_m": 8.35,
        "lat_m": 2.62,
        "ttc_s": 2.75,
        "closing_ms": 3.18,
        "speed_ms": 0.0,
        "risk": 0.3611
      }
    ]
  },
  "scenario": "sudden_brake",
  "vehicles": [
    {
      "id": "v19",
      "type": "vehicle",
      "blueprint": "vehicle.nissan.patrol",
      "loc": {
        "x": -48.409,
        "y": -50.11,
        "z": 0.3
      },
      "yaw": 98.04,
      "velocity": {
        "x": 0.0,
        "y": 0.0
      },
      "speed_ms": 0.0
    },
    {
      "id": "v5",
      "type": "vehicle",
      "blueprint": "vehicle.nissan.patrol",
      "loc": {
        "x": -41.664,
        "y": -40.493,
        "z": 0.3
      },
      "yaw": -89.57,
      "velocity": {
        "x": 0.0,
        "y": 0.0
      },
      "speed_ms": 0.0
    },
    {
      "id": "v38",
      "type": "vehicle",
      "blueprint": "vehicle.mercedes.coupe",
      "loc": {
        "x": -72.287,
        "y": -68.705,
        "z": 0.3
      },
      "yaw": 177.95,
      "velocity": {
        "x": 0.0,
        "y": 0.0
      },
      "speed_ms": 0.0
    },
    {
      "id": "v100",
      "type": "vehicle",
      "blueprint": "vehicle.volkswagen.t2_2021",
      "loc": {
        "x": -69.971,
        "y": -68.724,
        "z": 0.3
      },
      "yaw": -179.4,
      "velocity": {
        "x": 0.0,
        "y": 0.0
      },
      "speed_ms": 0.0
    },
    {
      "id": "v103",
      "type": "vehicle",
      "blueprint": "vehicle.mercedes.coupe_2020",
      "loc": {
        "x": -41.698,
        "y": -36.042,
        "z": 0.3
      },
      "yaw": -89.57,
      "velocity": {
        "x": 0.0,
        "y": 0.0
      },
      "speed_ms": 0.0
    },
    {
      "id": "v105",
      "type": "vehicle",
      "blueprint": "vehicle.ford.mustang",
      "loc": {
        "x": -64.337,
        "y": -68.665,
        "z": 0.3
      },
      "yaw": -179.4,
      "velocity": {
        "x": 0.0,
        "y": 0.0
      },
      "speed_ms": 0.0
    },
    {
      "id": "v123",
      "type": "vehicle",
      "blueprint": "vehicle.nissan.patrol",
      "loc": {
        "x": -64.432,
        "y": -68.666,
        "z": 0.3
      },
      "yaw": -179.4,
      "velocity": {
        "x": 0.0,
        "y": 0.0
      },
      "speed_ms": 0.0
    },
    {
      "id": "v112",
      "type": "vehicle",
      "blueprint": "vehicle.volkswagen.t2",
      "loc": {
        "x": -42.269,
        "y": -57.935,
        "z": 0.3
      },
      "yaw": 0.6,
      "velocity": {
        "x": 0.0,
        "y": 0.0
      },
      "speed_ms": 0.0
    },
    {
      "id": "v116",
      "type": "vehicle",
      "blueprint": "vehicle.toyota.prius",
      "loc": {
        "x": -38.262,
        "y": -57.893,
        "z": 0.3
      },
      "yaw": 0.6,
      "velocity": {
        "x": 0.0,
        "y": 0.0
      },
      "speed_ms": 0.0
    },
    {
      "id": "v150",
      "type": "vehicle",
      "blueprint": "vehicle.volkswagen.t2",
      "loc": {
        "x": -49.875,
        "y": -68.514,
        "z": 0.3
      },
      "yaw": -179.4,
      "velocity": {
        "x": 0.0,
        "y": 0.0
      },
      "speed_ms": 0.0
    },
    {
      "id": "v135",
      "type": "vehicle",
      "blueprint": "vehicle.audi.etron",
      "loc": {
        "x": -61.253,
        "y": -65.133,
        "z": 0.3
      },
      "yaw": -179.4,
      "velocity": {
        "x": 0.0,
        "y": 0.0
      },
      "speed_ms": 0.0
    },
    {
      "id": "v199",
      "type": "vehicle",
      "blueprint": "vehicle.micro.microlino",
      "loc": {
        "x": -74.584,
        "y": -68.557,
        "z": 0.3
      },
      "yaw": 174.66,
      "velocity": {
        "x": 0.0,
        "y": 0.0
      },
      "speed_ms": 0.0
    },
    {
      "id": "v113",
      "type": "vehicle",
      "blueprint": "vehicle.lincoln.mkz_2020",
      "loc": {
        "x": -41.667,
        "y": -40.128,
        "z": 0.3
      },
      "yaw": -89.57,
      "velocity": {
        "x": 0.0,
        "y": 0.0
      },
      "speed_ms": 0.0
    },
    {
      "id": "v134",
      "type": "vehicle",
      "blueprint": "vehicle.dodge.charger_police_2020",
      "loc": {
        "x": -68.187,
        "y": -68.705,
        "z": 0.3
      },
      "yaw": -179.4,
      "velocity": {
        "x": 0.0,
        "y": 0.0
      },
      "speed_ms": 0.0
    },
    {
      "id": "v128",
      "type": "vehicle",
      "blueprint": "vehicle.volkswagen.t2_2021",
      "loc": {
        "x": -47.565,
        "y": -53.722,
        "z": 0.3
      },
      "yaw": 108.25,
      "velocity": {
        "x": 0.0,
        "y": 0.0
      },
      "speed_ms": 0.0
    },
    {
      "id": "v170",
      "type": "vehicle",
      "blueprint": "vehicle.micro.microlino",
      "loc": {
        "x": -39.284,
        "y": -51.488,
        "z": 0.3
      },
      "yaw": -57.92,
      "velocity": {
        "x": 0.0,
        "y": 0.0
      },
      "speed_ms": 0.0
    },
    {
      "id": "v136",
      "type": "vehicle",
      "blueprint": "vehicle.bmw.grandtourer",
      "loc": {
        "x": -41.624,
        "y": -45.783,
        "z": 0.3
      },
      "yaw": -89.57,
      "velocity": {
        "x": 0.0,
        "y": 0.0
      },
      "speed_ms": 0.0
    },
    {
      "id": "v137",
      "type": "vehicle",
      "blueprint": "vehicle.dodge.charger_2020",
      "loc": {
        "x": -41.345,
        "y": -50.278,
        "z": 0.3
      },
      "yaw": -78.99,
      "velocity": {
        "x": 0.0,
        "y": 0.0
      },
      "speed_ms": 0.0
    },
    {
      "id": "v139",
      "type": "vehicle",
      "blueprint": "vehicle.mini.cooper_s",
      "loc": {
        "x": -45.959,
        "y": -55.758,
        "z": 0.3
      },
      "yaw": -106.35,
      "velocity": {
        "x": 0.0,
        "y": 0.0
      },
      "speed_ms": 0.0
    },
    {
      "id": "v138",
      "type": "vehicle",
      "blueprint": "vehicle.dodge.charger_police_2020",
      "loc": {
        "x": -41.744,
        "y": -29.967,
        "z": 0.3
      },
      "yaw": -89.57,
      "velocity": {
        "x": 0.0,
        "y": 0.0
      },
      "speed_ms": 0.0
    },
    {
      "id": "v140",
      "type": "vehicle",
      "blueprint": "vehicle.ford.mustang",
      "loc": {
        "x": -41.652,
        "y": -42.144,
        "z": 0.3
      },
      "yaw": -89.57,
      "velocity": {
        "x": 0.0,
        "y": 0.0
      },
      "speed_ms": 0.0
    },
    {
      "id": "v251",
      "type": "vehicle",
      "blueprint": "vehicle.micro.microlino",
      "loc": {
        "x": -56.997,
        "y": -67.947,
        "z": 0.3
      },
      "yaw": -162.69,
      "velocity": {
        "x": 0.0,
        "y": 0.0
      },
      "speed_ms": 0.0
    },
    {
      "id": "v154",
      "type": "vehicle",
      "blueprint": "vehicle.volkswagen.t2_2021",
      "loc": {
        "x": -37.161,
        "y": -54.199,
        "z": 0.3
      },
      "yaw": -46.16,
      "velocity": {
        "x": 0.0,
        "y": 0.0
      },
      "speed_ms": 0.0
    },
    {
      "id": "v319",
      "type": "vehicle",
      "blueprint": "vehicle.micro.microlino",
      "loc": {
        "x": -76.868,
        "y": -68.277,
        "z": 0.3
      },
      "yaw": 171.36,
      "velocity": {
        "x": 0.0,
        "y": 0.0
      },
      "speed_ms": 0.0
    },
    {
      "id": "v158",
      "type": "vehicle",
      "blueprint": "vehicle.audi.a2",
      "loc": {
        "x": -60.011,
        "y": -68.62,
        "z": 0.3
      },
      "yaw": -179.4,
      "velocity": {
        "x": 0.0,
        "y": 0.0
      },
      "speed_ms": 0.0
    }
  ],
  "pedestrians": [
    {
      "id": "p0",
      "type": "pedestrian",
      "blueprint": "walker.pedestrian.0051",
      "loc": {
        "x": -27.418,
        "y": 2.2,
        "z": 1.089
      },
      "yaw": 0.28,
      "velocity": {
        "x": 0.0,
        "y": 0.0
      },
      "speed_ms": 0.0
    },
    {
      "id": "p1",
      "type": "pedestrian",
      "blueprint": "walker.pedestrian.0003",
      "loc": {
        "x": -60.492,
        "y": -22.29,
        "z": 1.089
      },
      "yaw": 84.84,
      "velocity": {
        "x": 0.0,
        "y": 0.0
      },
      "speed_ms": 0.0
    },
    {
      "id": "p10",
      "type": "pedestrian",
      "blueprint": "walker.pedestrian.0004",
      "loc": {
        "x": -45.503,
        "y": -65.345,
        "z": 0.302
      },
      "yaw": -19.22,
      "velocity": {
        "x": 0.0,
        "y": 0.0
      },
      "speed_ms": 0.0
    },
    {
      "id": "p11",
      "type": "pedestrian",
      "blueprint": "walker.pedestrian.0051",
      "loc": {
        "x": -32.685,
        "y": 1.118,
        "z": 1.089
      },
      "yaw": 26.74,
      "velocity": {
        "x": 0.0,
        "y": 0.0
      },
      "speed_ms": 0.0
    },
    {
      "id": "p12",
      "type": "pedestrian",
      "blueprint": "walker.pedestrian.0022",
      "loc": {
        "x": -34.345,
        "y": -36.498,
        "z": 1.089
      },
      "yaw": -76.66,
      "velocity": {
        "x": 0.0,
        "y": 0.0
      },
      "speed_ms": 0.0
    },
    {
      "id": "p13",
      "type": "pedestrian",
      "blueprint": "walker.pedestrian.0018",
      "loc": {
        "x": -32.412,
        "y": -49.326,
        "z": 1.089
      },
      "yaw": -67.91,
      "velocity": {
        "x": 0.0,
        "y": 0.0
      },
      "speed_ms": 0.0
    },
    {
      "id": "p14",
      "type": "pedestrian",
      "blueprint": "walker.pedestrian.0017",
      "loc": {
        "x": -64.097,
        "y": 3.844,
        "z": 1.089
      },
      "yaw": -3.52,
      "velocity": {
        "x": 0.0,
        "y": 0.0
      },
      "speed_ms": 0.0
    },
    {
      "id": "p15",
      "type": "pedestrian",
      "blueprint": "walker.pedestrian.0008",
      "loc": {
        "x": -60.824,
        "y": -5.438,
        "z": 1.089
      },
      "yaw": 97.62,
      "velocity": {
        "x": 0.0,
        "y": 0.0
      },
      "speed_ms": 0.0
    },
    {
      "id": "p16",
      "type": "pedestrian",
      "blueprint": "walker.pedestrian.0051",
      "loc": {
        "x": -33.455,
        "y": -44.914,
        "z": 1.089
      },
      "yaw": -75.57,
      "velocity": {
        "x": 0.0,
        "y": 0.0
      },
      "speed_ms": 0.0
    },
    {
      "id": "p17",
      "type": "pedestrian",
      "blueprint": "walker.pedestrian.0029",
      "loc": {
        "x": -35.026,
        "y": -38.536,
        "z": 1.089
      },
      "yaw": 82.86,
      "velocity": {
        "x": 0.0,
        "y": 0.0
      },
      "speed_ms": 0.0
    },
    {
      "id": "p18",
      "type": "pedestrian",
      "blueprint": "walker.pedestrian.0009",
      "loc": {
        "x": -61.544,
        "y": -8.728,
        "z": 0.709
      },
      "yaw": 94.28,
      "velocity": {
        "x": 0.0,
        "y": 0.0
      },
      "speed_ms": 0.0
    },
    {
      "id": "p19",
      "type": "pedestrian",
      "blueprint": "walker.pedestrian.0025",
      "loc": {
        "x": -61.368,
        "y": -45.916,
        "z": 1.089
      },
      "yaw": -155.0,
      "velocity": {
        "x": 0.0,
        "y": 0.0
      },
      "speed_ms": 0.0
    },
    {
      "id": "p2",
      "type": "pedestrian",
      "blueprint": "walker.pedestrian.0038",
      "loc": {
        "x": -58.673,
        "y": -46.164,
        "z": 1.089
      },
      "yaw": -162.47,
      "velocity": {
        "x": 0.0,
        "y": 0.0
      },
      "speed_ms": 0.0
    },
    {
      "id": "p20",
      "type": "pedestrian",
      "blueprint": "walker.pedestrian.0036",
      "loc": {
        "x": -51.739,
        "y": -48.3,
        "z": 0.987
      },
      "yaw": -55.83,
      "velocity": {
        "x": 0.0,
        "y": 0.0
      },
      "speed_ms": 0.0
    },
    {
      "id": "p21",
      "type": "pedestrian",
      "blueprint": "walker.pedestrian.0015",
      "loc": {
        "x": -30.818,
        "y": -61.046,
        "z": 0.939
      },
      "yaw": 87.78,
      "velocity": {
        "x": 0.0,
        "y": 0.0
      },
      "speed_ms": 0.0
    },
    {
      "id": "p22",
      "type": "pedestrian",
      "blueprint": "walker.pedestrian.0016",
      "loc": {
        "x": -50.92,
        "y": -48.582,
        "z": 0.953
      },
      "yaw": -107.02,
      "velocity": {
        "x": 0.0,
        "y": 0.0
      },
      "speed_ms": 0.0
    },
    {
      "id": "p24",
      "type": "pedestrian",
      "blueprint": "walker.pedestrian.0038",
      "loc": {
        "x": -34.489,
        "y": -28.505,
        "z": 1.089
      },
      "yaw": 86.41,
      "velocity": {
        "x": 0.0,
        "y": 0.0
      },
      "speed_ms": 0.0
    }
  ],
  "total_actors": 42,
  "sensors": {
    "rgb": {
      "file": "rgb/066729.png",
      "width": 800,
      "height": 600,
      "fov": 90
    },
    "depth": {
      "file": "depth/066729.png",
      "unit": "mm_uint16",
      "fx": 400.0,
      "fy": 300.0,
      "cx": 400,
      "cy": 300
    },
    "lidar": {
      "file": "lidar/066729.npy",
      "columns": [
        "x",
        "y",
        "z",
        "intensity"
      ],
      "num_points": 29267
    }
  },
  "yolo_detections": []
}